test_run_dir/AdderTest276422405/AdderS.v
module AdderS(
  input        clock,
  input        reset,
  input  [7:0] io_a,
  input  [7:0] io_b,
  output [7:0] io_out
);
  assign io_out = io_a + io_b; // @[Accum.scala 50:24]
endmodule

test_run_dir/AdderTest276422405/AdderS.vcd
$version Generated by VerilatedVcd $end
$date Fri May  6 22:15:09 2022
 $end
$timescale   1ps $end

 $scope module TOP $end
  $var wire  1 # clock $end
  $var wire  8 % io_a [7:0] $end
  $var wire  8 & io_b [7:0] $end
  $var wire  8 ' io_out [7:0] $end
  $var wire  1 $ reset $end
  $scope module AdderS $end
   $var wire  1 # clock $end
   $var wire  8 % io_a [7:0] $end
   $var wire  8 & io_b [7:0] $end
   $var wire  8 ' io_out [7:0] $end
   $var wire  1 $ reset $end
  $upscope $end
 $upscope $end
$enddefinitions $end


#0
0#
1$
b00000000 %
b00000000 &
b00000000 '
#1
1#
#2
0#
#3
1#
#4
0#
#5
1#
#6
0#
#7
1#
#8
0#
#9
1#
#10
0#
0$
b11010101 %
b11011011 &
b10110000 '
#11
1#
#12
0#
b00110111 %
b00110000 &
b01100111 '
#13
1#
#14
0#
b01000101 %
b00011111 &
b01100100 '
#15
1#
#16
0#
b00100011 %
b10100000 &
b11000011 '
#17
1#
#18
0#
b11111110 %
b01011100 &
b01011010 '
#19
1#
#20
0#
b00000010 %
b11101111 &
b11110001 '
#21
1#
#22
0#
b01110010 %
b11001011 &
b00111101 '
#23
1#
#24
0#
b10111101 %
b10000001 &
b00111110 '
#25
1#
#26
0#
b10000011 %
b01111110 &
b00000001 '
#27
1#
#28
0#
b01010010 %
b01101010 &
b10111100 '
#29
1#
#30
0#
b11011101 %
b00100011 &
b00000000 '
#31
1#
#32
0#
b01010000 %
b00011110 &
b01101110 '
#33
1#
#34
0#
b01110111 %
b00001101 &
b10000100 '
#35
1#
#36
0#
b11100011 %
b01001000 &
b00101011 '
#37
1#
#38
0#
b01110010 %
b11111110 &
b01110000 '
#39
1#
#40
0#
b11010101 %
b01100101 &
b00111010 '
#41
1#
#42
0#
b01001111 %
b01001100 &
b10011011 '
#43
1#
#44
0#
b11000000 %
b00100100 &
b11100100 '
#45
1#
#46
0#
b11010101 %
b11111101 &
b11010010 '
#47
1#
#48
0#
b10011001 %
b01101100 &
b00000101 '
#49
1#
#50
0#
b00111000 %
b00011111 &
b01010111 '
#51
1#
#52
0#
b11001110 %
b01011000 &
b00100110 '
#53
1#
#54
0#
b01100110 %
b10111011 &
b00100001 '
#55
1#
#56
0#
b10011111 %
b01111011 &
b00011010 '
#57
1#
#58
0#
b01101001 %
b01101100 &
b11010101 '
#59
1#
#60
0#
b10000000 %
b11101101 &
b01101101 '
#61
1#
#62
0#
b11100011 %
b10101011 &
b10001110 '
#63
1#
#64
0#
b01110011 %
b00001110 &
b10000001 '
#65
1#
#66
0#
b00111000 %
b01000110 '
#67
1#
#68
0#
b00010010 %
b10100001 &
b10110011 '
#69
1#
#70
0#
b10000010 %
b10010010 &
b00010100 '
#71
1#
#72
0#
b10100100 %
b01110100 &
b00011000 '
#73
1#
#74
0#
b10111010 %
b10001000 &
b01000010 '
#75
1#
#76
0#
b00110010 %
b10100101 &
b11010111 '
#77
1#
#78
0#
b10111100 %
b01111010 &
b00110110 '
#79
1#
#80
0#
b00011001 %
b00111011 &
b01010100 '
#81
1#
#82
0#
b11001110 %
b11011011 &
b10101001 '
#83
1#
#84
0#
b11011110 %
b10011011 &
b01111001 '
#85
1#
#86
0#
b00011001 %
b01010000 &
b01101001 '
#87
1#
#88
0#
b10000001 %
b00010010 &
b10010011 '
#89
1#
#90
0#
b11000101 %
b10101001 &
b01101110 '
#91
1#
#92
0#
b11000001 %
b10001001 &
b01001010 '
#93
1#
#94
0#
b00100101 %
b01011011 &
b10000000 '
#95
1#
#96
0#
b00110001 %
b00001001 &
b00111010 '
#97
1#
#98
0#
b01001110 %
b00110101 &
b10000011 '
#99
1#
#100
0#
b11101101 %
b00001011 &
b11111000 '
#101
1#
#102
0#
b11110010 %
b00100110 &
b00011000 '
#103
1#
#104
0#
b01100100 %
b00001010 &
b01101110 '
#105
1#
#106
0#
b11100101 %
b10000101 &
b01101010 '
#107
1#
#108
0#
b00110110 %
b10111000 &
b11101110 '
#109
1#
#110
0#
b11001001 %
b01110101 &
b00111110 '
#111
1#
#112
0#
b11001011 %
b01000101 &
b00010000 '
#113
1#
#114
0#
b11000100 %
b10000000 &
b01000100 '
#115
1#
#116
0#
b11001110 %
b10111110 &
b10001100 '
#117
1#
#118
0#
b01000100 %
b01110111 &
b10111011 '
#119
1#
#120
0#
b11010110 %
b10110011 &
b10001001 '
#121
1#
#122
0#
b01000100 %
b10010100 &
b11011000 '
#123
1#
#124
0#
b11110101 %
b00100000 &
b00010101 '
#125
1#
#126
0#
b01101100 %
b01001101 &
b10111001 '
#127
1#
#128
0#
b11010111 %
b01011110 &
b00110101 '
#129
1#
#130
0#
b10111000 %
b00100000 &
b11011000 '
#131
1#
#132
0#
b11000001 %
b10010001 &
b01010010 '
#133
1#
#134
0#
b10011000 %
b11001001 &
b01100001 '
#135
1#
#136
0#
b01110110 %
b00010000 &
b10000110 '
#137
1#
#138
0#
b11110010 %
b10001110 &
b10000000 '
#139
1#
#140
0#
b00000011 %
b10110111 &
b10111010 '
#141
1#
#142
0#
b01010000 %
b00111000 &
b10001000 '
#143
1#
#144
0#
b01101101 %
b00000010 &
b01101111 '
#145
1#
#146
0#
b00011000 %
b11100101 &
b11111101 '
#147
1#
#148
0#
b01010001 %
b11111101 &
b01001110 '
#149
1#
#150
0#
b11110111 %
b10111111 &
b10110110 '
#151
1#
#152
0#
b10110101 %
b11101110 &
b10100011 '
#153
1#
#154
0#
b11111001 %
b00111111 &
b00111000 '
#155
1#
#156
0#
b00001110 %
b01100001 &
b01101111 '
#157
1#
#158
0#
b11100010 %
b00011011 &
b11111101 '
#159
1#
#160
0#
b10001011 %
b00101110 &
b10111001 '
#161
1#
#162
0#
b10110010 %
b10001100 &
b00111110 '
#163
1#
#164
0#
b00010110 %
b01111011 &
b10010001 '
#165
1#
#166
0#
b00101110 %
b00011010 &
b01001000 '
#167
1#
#168
0#
b11001011 %
b11111101 &
b11001000 '
#169
1#
#170
0#
b01101101 %
b11000010 &
b00101111 '
#171
1#
#172
0#
b01010111 %
b00001001 &
b01100000 '
#173
1#
#174
0#
b00001010 %
b10001100 &
b10010110 '
#175
1#
#176
0#
b00011100 %
b11100101 &
b00000001 '
#177
1#
#178
0#
b11100111 %
b10001111 &
b01110110 '
#179
1#
#180
0#
b01001110 %
b01111001 &
b11000111 '
#181
1#
#182
0#
b00000100 %
b00100000 &
b00100100 '
#183
1#
#184
0#
b01011001 %
b00110001 &
b10001010 '
#185
1#
#186
0#
b10110011 %
b10001101 &
b01000000 '
#187
1#
#188
0#
b10110101 %
b10101001 &
b01011110 '
#189
1#
#190
0#
b10100001 %
b11011111 &
b10000000 '
#191
1#
#192
0#
b01101010 %
b11011011 &
b01000101 '
#193
1#
#194
0#
b01101011 %
b11010110 &
b01000001 '
#195
1#
#196
0#
b00111110 %
b11000001 &
b11111111 '
#197
1#
#198
0#
b10110011 %
b11111000 &
b10101011 '
#199
1#
#200
0#
b10000011 %
b11010111 &
b01011010 '
#201
1#
#202
0#
b10001101 %
b11110010 &
b01111111 '
#203
1#
#204
0#
b01011010 %
b01011011 &
b10110101 '
#205
1#
#206
0#
b11111000 %
b10111110 &
b10110110 '
#207
1#
#208
0#
b01011100 %
b10100011 &
b11111111 '
