test_run_dir/AluTest875848327/AluSimple.v
module AluSimple(
  input        clock,
  input        reset,
  input  [7:0] io_rs1,
  input  [7:0] io_rs2,
  input  [3:0] io_alu_op,
  output [7:0] io_out,
  output [7:0] io_sum
);
  wire [4:0] shamt = io_rs2[4:0]; // @[Alu.scala 41:27]
  wire [7:0] _T_1 = io_rs1 + io_rs2; // @[Alu.scala 47:44]
  wire [7:0] _T_3 = io_rs1 - io_rs2; // @[Alu.scala 48:44]
  wire [7:0] _T_4 = io_rs1 >> shamt; // @[Alu.scala 49:44]
  wire [38:0] _GEN_0 = {{31'd0}, io_rs1}; // @[Alu.scala 50:44]
  wire [38:0] _T_5 = _GEN_0 << shamt; // @[Alu.scala 50:44]
  wire  _T_8 = $signed(io_rs1) < $signed(io_rs2); // @[Alu.scala 51:51]
  wire  _T_9 = io_rs1 < io_rs2; // @[Alu.scala 52:45]
  wire [7:0] _T_10 = io_rs1 & io_rs2; // @[Alu.scala 53:44]
  wire [7:0] _T_11 = io_rs1 | io_rs2; // @[Alu.scala 54:43]
  wire [7:0] _T_12 = io_rs1 ^ io_rs2; // @[Alu.scala 55:44]
  wire [7:0] _T_14 = 4'h0 == io_alu_op ? _T_1 : io_rs2; // @[Mux.scala 80:57]
  wire [7:0] _T_16 = 4'h1 == io_alu_op ? _T_3 : _T_14; // @[Mux.scala 80:57]
  wire [7:0] _T_18 = 4'h9 == io_alu_op ? _T_4 : _T_16; // @[Mux.scala 80:57]
  wire [38:0] _T_20 = 4'h8 == io_alu_op ? _T_5 : {{31'd0}, _T_18}; // @[Mux.scala 80:57]
  wire [38:0] _T_22 = 4'h5 == io_alu_op ? {{38'd0}, _T_8} : _T_20; // @[Mux.scala 80:57]
  wire [38:0] _T_24 = 4'h7 == io_alu_op ? {{38'd0}, _T_9} : _T_22; // @[Mux.scala 80:57]
  wire [38:0] _T_26 = 4'h2 == io_alu_op ? {{31'd0}, _T_10} : _T_24; // @[Mux.scala 80:57]
  wire [38:0] _T_28 = 4'h3 == io_alu_op ? {{31'd0}, _T_11} : _T_26; // @[Mux.scala 80:57]
  wire [38:0] _T_30 = 4'h4 == io_alu_op ? {{31'd0}, _T_12} : _T_28; // @[Mux.scala 80:57]
  wire [38:0] _T_32 = 4'ha == io_alu_op ? {{31'd0}, io_rs1} : _T_30; // @[Mux.scala 80:57]
  wire [7:0] _T_35 = 8'h0 - io_rs2; // @[Alu.scala 60:46]
  wire [7:0] _T_36 = io_alu_op[0] ? _T_35 : io_rs2; // @[Alu.scala 60:31]
  assign io_out = _T_32[7:0]; // @[Alu.scala 43:16]
  assign io_sum = io_rs1 + _T_36; // @[Alu.scala 60:26]
endmodule

test_run_dir/AluTest875848327/AluSimple.vcd
$version Generated by VerilatedVcd $end
$date Sun May  8 21:23:36 2022
 $end
$timescale   1ps $end

 $scope module TOP $end
  $var wire  1 # clock $end
  $var wire  4 ' io_alu_op [3:0] $end
  $var wire  8 ( io_out [7:0] $end
  $var wire  8 % io_rs1 [7:0] $end
  $var wire  8 & io_rs2 [7:0] $end
  $var wire  8 ) io_sum [7:0] $end
  $var wire  1 $ reset $end
  $scope module AluSimple $end
   $var wire  1 # clock $end
   $var wire  4 ' io_alu_op [3:0] $end
   $var wire  8 ( io_out [7:0] $end
   $var wire  8 % io_rs1 [7:0] $end
   $var wire  8 & io_rs2 [7:0] $end
   $var wire  8 ) io_sum [7:0] $end
   $var wire  1 $ reset $end
   $var wire  5 * shamt [4:0] $end
  $upscope $end
 $upscope $end
$enddefinitions $end


#0
0#
1$
b00000000 %
b00000000 &
b0000 '
b00000000 (
b00000000 )
b00000 *
#1
1#
#2
0#
#3
1#
#4
0#
#5
1#
#6
0#
#7
1#
#8
0#
#9
1#
#10
0#
0$
b11010111 %
b10110011 &
b1010 '
b11010111 (
b10001010 )
b10011 *
#11
1#
#12
0#
b10110101 %
b11000110 &
b1000 '
b01000000 (
b01111011 )
b00110 *
#13
1#
#14
0#
b01101100 %
b11001010 &
b0000 '
b00110110 (
b00110110 )
b01010 *
#15
1#
#16
0#
b00100111 %
b01000101 &
b1000 '
b11100000 (
b01101100 )
b00101 *
#17
1#
#18
0#
b11101011 %
b11010100 &
b0100 '
b00111111 (
b10111111 )
b10100 *
#19
1#
#20
0#
b01101101 %
b01111111 &
b1011 '
b01111111 (
b11101110 )
b11111 *
#21
1#
#22
0#
b01101001 %
b01100010 &
b0100 '
b00001011 (
b11001011 )
b00010 *
#23
1#
#24
0#
b10010001 %
b11011111 &
b1010 '
b10010001 (
b01110000 )
b11111 *
#25
1#
#26
0#
b00111101 %
b00000100 &
b0110 '
b00000100 (
b01000001 )
b00100 *
#27
1#
#28
0#
b11001001 %
b01001001 &
b1010 '
b11001001 (
b00010010 )
b01001 *
#29
1#
#30
0#
b00011110 %
b11011111 &
b0000 '
b11111101 (
b11111101 )
b11111 *
#31
1#
#32
0#
b01000101 %
b11101101 &
b1011 '
b11101101 (
b01011000 )
b01101 *
#33
1#
#34
0#
b10110011 %
b10111011 &
b0110 '
b10111011 (
b01101110 )
b11011 *
#35
1#
#36
0#
b11110110 %
b11000000 &
b1000 '
b11110110 (
b10110110 )
b00000 *
#37
1#
#38
0#
b00101110 %
b00000100 &
b0001 '
b00101010 (
b00101010 )
b00100 *
#39
1#
#40
0#
b00111110 %
b11101011 &
b0110 '
b11101011 (
b00101001 )
b01011 *
#41
1#
#42
0#
b11100001 %
b10001011 &
b1001 '
b00000000 (
b01010110 )
#43
1#
#44
0#
b10101011 %
b00000011 &
b1011 '
b00000011 (
b10101000 )
b00011 *
#45
1#
#46
0#
b00001101 %
b10101100 &
b1010 '
b00001101 (
b10111001 )
b01100 *
#47
1#
#48
0#
b11111010 %
b10111011 &
b0100 '
b01000001 (
b10110101 )
b11011 *
#49
1#
#50
0#
b10111011 %
b00010011 &
b10101000 (
b11001110 )
b10011 *
#51
1#
#52
0#
b11101000 %
b00101000 &
b1010 '
b11101000 (
b00010000 )
b01000 *
#53
1#
#54
0#
b01010110 %
b11111100 &
b0010 '
b01010100 (
b01010010 )
b11100 *
#55
1#
#56
0#
b11100111 %
b00111001 &
b1010 '
b11100111 (
b00100000 )
b11001 *
#57
1#
#58
0#
b01000101 %
b00011100 &
b0001 '
b00101001 (
b00101001 )
b11100 *
#59
1#
#60
0#
b11111111 %
b11011101 &
b0011 '
b11111111 (
b00100010 )
b11101 *
#61
1#
#62
0#
b01100000 %
b11001101 &
b1011 '
b11001101 (
b10010011 )
b01101 *
#63
1#
#64
0#
b10110101 %
b01111010 &
b0010 '
b00110000 (
b00101111 )
b11010 *
#65
1#
#66
0#
b11111101 %
b01111000 &
b01111000 (
b01110101 )
b11000 *
#67
1#
#68
0#
b11001110 %
b00000000 &
b0001 '
b11001110 (
b11001110 )
b00000 *
#69
1#
#70
0#
b01110110 %
b11011111 &
b1010 '
b01110110 (
b01010101 )
b11111 *
#71
1#
#72
0#
b11110010 %
b00100100 &
b1001 '
b00001111 (
b11001110 )
b00100 *
#73
1#
#74
0#
b10001011 %
b00110011 &
b0010 '
b00000011 (
b10111110 )
b10011 *
#75
1#
#76
0#
b10010001 %
b10001011 &
b1011 '
b10001011 (
b00000110 )
b01011 *
#77
1#
#78
0#
b11000100 %
b00111010 &
b0101 '
b00000001 (
b10001010 )
b11010 *
#79
1#
#80
0#
b11001100 %
b00100010 &
b0100 '
b11101110 (
b11101110 )
b00010 *
#81
1#
#82
0#
b01011110 %
b01011110 &
b1001 '
b00000000 (
b00000000 )
b11110 *
#83
1#
#84
0#
b01100110 %
b00010011 &
b0101 '
b01010011 )
b10011 *
#85
1#
#86
0#
b00100000 %
b00001100 &
b1000 '
b00101100 )
b01100 *
#87
1#
#88
0#
b00111110 %
b10110111 &
b1001 '
b10000111 )
b10111 *
#89
1#
#90
0#
b00011101 %
b11100001 &
b00001110 (
b00111100 )
b00001 *
#91
1#
#92
0#
b10110010 %
b11010010 &
b0101 '
b00000001 (
b11100000 )
b10010 *
#93
1#
#94
0#
b01010001 %
b01111100 &
b0001 '
b11010101 (
b11010101 )
b11100 *
#95
1#
#96
0#
b00110010 %
b00001100 &
b1010 '
b00110010 (
b00111110 )
b01100 *
#97
1#
#98
0#
b01011010 %
b01010101 &
b1000 '
b00000000 (
b10101111 )
b10101 *
#99
1#
#100
0#
b10001100 %
b10101010 &
b1010 '
b10001100 (
b00110110 )
b01010 *
#101
1#
#102
0#
b00011011 %
b01010001 &
b1000 '
b00000000 (
b01101100 )
b10001 *
#103
1#
#104
0#
b10100111 %
b10001011 &
b0110 '
b10001011 (
b00110010 )
b01011 *
#105
1#
#106
0#
b00010100 %
b10001110 &
b0101 '
b00000000 (
b10000110 )
b01110 *
#107
1#
#108
0#
b01110100 %
b00111001 &
b00111011 )
b11001 *
#109
1#
#110
0#
b00100010 %
b11000100 &
b0010 '
b11100110 )
b00100 *
#111
1#
#112
0#
b00010001 %
b10001011 &
b1000 '
b10011100 )
b01011 *
#113
1#
#114
0#
b00001110 %
b10111011 &
b1011 '
b10111011 (
b01010011 )
b11011 *
#115
1#
#116
0#
b01110001 %
b10111110 &
b0000 '
b00101111 (
b00101111 )
b11110 *
#117
1#
#118
0#
b11110100 %
b01111100 &
b0110 '
b01111100 (
b01110000 )
b11100 *
#119
1#
#120
0#
b00100110 %
b00101110 &
b0000 '
b01010100 (
b01010100 )
b01110 *
#121
1#
#122
0#
b10101100 %
b01001110 &
b0001 '
b01011110 (
b01011110 )
#123
1#
#124
0#
b01000001 %
b10101111 &
b10010010 (
b10010010 )
b01111 *
#125
1#
#126
0#
b00111001 %
b01001110 &
b1011 '
b01001110 (
b11101011 )
b01110 *
#127
1#
#128
0#
b11111110 %
b00000010 &
b0111 '
b00000000 (
b11111100 )
b00010 *
#129
1#
#130
0#
b01111110 %
b01010101 &
b1000 '
b11010011 )
b10101 *
#131
1#
#132
0#
b01111000 %
b00001001 &
b1011 '
b00001001 (
b01101111 )
b01001 *
#133
1#
#134
0#
b01010011 %
b11111100 &
b0010 '
b01010000 (
b01001111 )
b11100 *
#135
1#
#136
0#
b00101001 &
b0111 '
b00000000 (
b00101010 )
b01001 *
#137
1#
#138
0#
b00000010 %
b00000100 &
b0100 '
b00000110 (
b00000110 )
b00100 *
#139
1#
#140
0#
b10011101 %
b00011010 &
b1000 '
b00000000 (
b10110111 )
b11010 *
#141
1#
#142
0#
b10010000 %
b01110001 &
b1010 '
b10010000 (
b00000001 )
b10001 *
#143
1#
#144
0#
b01100101 %
b11011000 &
b01100101 (
b00111101 )
b11000 *
#145
1#
#146
0#
b10110110 %
b01000110 &
b0001 '
b01110000 (
b01110000 )
b00110 *
#147
1#
#148
0#
b01000011 %
b01101101 &
b1011 '
b01101101 (
b11010110 )
b01101 *
#149
1#
#150
0#
b11111101 %
b01011001 &
b01011001 (
b10100100 )
b11001 *
#151
1#
#152
0#
b00001000 %
b01110001 &
b1001 '
b00000000 (
b10010111 )
b10001 *
#153
1#
#154
0#
b01100010 %
b00011001 &
b1010 '
b01100010 (
b01111011 )
b11001 *
#155
1#
#156
0#
b00100100 %
b01111101 &
b0101 '
b00000001 (
b10100111 )
b11101 *
#157
1#
#158
0#
b01100111 %
b00111100 &
b1001 '
b00000000 (
b00101011 )
b11100 *
#159
1#
#160
0#
b11010100 %
b10101101 &
b0101 '
b00100111 )
b01101 *
#161
1#
#162
0#
b11010000 %
b01100010 &
b0100 '
b10110010 (
b00110010 )
b00010 *
#163
1#
#164
0#
b00000000 %
b01000100 &
b1011 '
b01000100 (
b10111100 )
b00100 *
#165
1#
#166
0#
b11111000 %
b11100000 &
b0011 '
b11111000 (
b00011000 )
b00000 *
#167
1#
#168
0#
b00111011 %
b11101000 &
b0010 '
b00101000 (
b00100011 )
b01000 *
#169
1#
#170
0#
b10001001 &
b1000 '
b00000000 (
b11000100 )
b01001 *
#171
1#
#172
0#
b00010001 %
b11010010 &
b0111 '
b00000001 (
b00111111 )
b10010 *
#173
1#
#174
0#
b10101111 %
b01111100 &
b1011 '
b01111100 (
b00110011 )
b11100 *
#175
1#
#176
0#
b00010010 %
b01011111 &
b01011111 (
b10110011 )
b11111 *
#177
1#
#178
0#
b11001101 %
b01001111 &
b0000 '
b00011100 (
b00011100 )
b01111 *
#179
1#
#180
0#
b01001110 %
b00111011 &
b1001 '
b00000000 (
b00010011 )
b11011 *
#181
1#
#182
0#
b01100111 %
b01100101 &
b0101 '
b00000010 )
b00101 *
#183
1#
#184
0#
b10011100 %
b11110010 &
b00000001 (
b10101010 )
b10010 *
#185
1#
#186
0#
b00111011 %
b11111111 &
b1001 '
b00000000 (
b00111100 )
b11111 *
#187
1#
#188
0#
b11101011 %
b11001001 &
b1000 '
b10110100 )
b01001 *
#189
1#
#190
0#
b01111011 %
b01011100 &
b1001 '
b00011111 )
b11100 *
#191
1#
#192
0#
b01100110 %
b00101010 &
b1000 '
b10010000 )
b01010 *
#193
1#
#194
0#
b11010000 %
b11100100 &
b0101 '
b00000001 (
b11101100 )
b00100 *
#195
1#
#196
0#
b01110110 %
b10001001 &
b0110 '
b10001001 (
b11111111 )
b01001 *
#197
1#
#198
0#
b11110010 %
b10010100 &
b0100 '
b01100110 (
b10000110 )
b10100 *
#199
1#
#200
0#
b01010100 %
b10101000 &
b1000 '
b00000000 (
b11111100 )
b01000 *
#201
1#
#202
0#
b00001100 %
b00010111 &
b0100 '
b00011011 (
b00100011 )
b10111 *
#203
1#
#204
0#
b11111000 %
b00110111 &
b0101 '
b00000001 (
b11000001 )
#205
1#
#206
0#
b11001011 %
b11001111 &
b0011 '
b11001111 (
b11111100 )
b01111 *
#207
1#
#208
0#
b00101100 %
b11001001 &
b0001 '
b01100011 (
b01100011 )
b01001 *
